tofu/__init__.py
tofu/tofu.py
tofu_openstack-1.3.0.data/scripts/tofu.py
tofu_openstack-1.3.0.dist-info/LICENSE
tofu_openstack-1.3.0.dist-info/METADATA
tofu_openstack-1.3.0.dist-info/WHEEL
tofu_openstack-1.3.0.dist-info/top_level.txt
tofu_openstack-1.3.0.dist-info/RECORD
