Metadata-Version: 2.1
Name: tofu-openstack
Version: 1.3.0
Summary: A terraform openstack dynamic inventory for ansible
Home-page: https://github.com/shalomb/tofu
Author: Shalom Bhooshi
Author-email: s.bhooshi@gmail.com
License: Apache License 2.0
Platform: UNKNOWN
Requires-Dist: pyyaml
